octopuspy/__init__.py
octopuspy/bandstructure.py
octopuspy/eigenvalues.py
octopuspy/info.py
octopuspy/results.py
scripts/__init__.py
scripts/octo2vasp.py
tests/__init__.py
tests/test_bandstructure.py
tests/test_eigenvalues.py
tests/test_info.py
tests/test_octo2vasp.py
tests/test_results.py
octopuspy-1.0.3.dist-info/LICENSE
octopuspy-1.0.3.dist-info/METADATA
octopuspy-1.0.3.dist-info/WHEEL
octopuspy-1.0.3.dist-info/top_level.txt
octopuspy-1.0.3.dist-info/RECORD
