Metadata-Version: 2.1
Name: octopuspy
Version: 1.0.3
Summary: Python package for manipulating Octopus output files
Home-page: https://github.com/afatt/octopuspy
Author: Austin Fatt
Author-email: afatt90@gmail.com, austin.d.fatt@navy.mil
License: MIT
Download-URL: https://github.com/afatt/octopuspy/archive/refs/tags/1.0.3.tar.gz
Keywords: octopuspy
Platform: UNKNOWN
Classifier: Programming Language :: Python :: 3.7
Requires-Python: >=3.7
License-File: LICENSE
Requires-Dist: coverage (==4.3.4)
Requires-Dist: cycler
Requires-Dist: kiwisolver
Requires-Dist: matplotlib
Requires-Dist: numpy
Requires-Dist: pyparsing
Requires-Dist: python-dateutil
Requires-Dist: six
